LICENSE
MANIFEST.in
README.md
setup.py
pyntercom/__init__.py
pyntercom/client.py
pyntercom/encoder.py
pyntercom.egg-info/PKG-INFO
pyntercom.egg-info/SOURCES.txt
pyntercom.egg-info/dependency_links.txt
pyntercom.egg-info/requires.txt
pyntercom.egg-info/top_level.txt