Metadata-Version: 1.1
Name: pyntercom
Version: 0.0.1
Summary: Python HTTP client for Intercom.io
Home-page: https://github.com/jarcoal/pyntercom
Author: Jared Morse
Author-email: jarcoal@gmail.com
License: MIT
Keywords: python,intercom.io
Platform: UNKNOWN
Classifier: Programming Language :: Python
Classifier: Topic :: Software Development :: Libraries :: Python Modules
